cellygon/__init__.py
cellygon/cellygon.py
cellygon/cellygonize.py
cellygon/cli.py
cellygon-0.1.5.dist-info/AUTHORS.rst
cellygon-0.1.5.dist-info/LICENSE
cellygon-0.1.5.dist-info/METADATA
cellygon-0.1.5.dist-info/WHEEL
cellygon-0.1.5.dist-info/entry_points.txt
cellygon-0.1.5.dist-info/top_level.txt
cellygon-0.1.5.dist-info/RECORD
