Metadata-Version: 2.1
Name: cellygon
Version: 0.1.5
Summary: create cellular meshes from segmented cells
Home-page: https://github.com/supersubscript/cellygon
Author: Henrik Åhl
Author-email: henrikaahl@gmail.com
License: GNU General Public License v3
Keywords: cellygon
Classifier: Development Status :: 2 - Pre-Alpha
Classifier: Intended Audience :: Developers
Classifier: License :: OSI Approved :: GNU General Public License v3 (GPLv3)
Classifier: Natural Language :: English
Classifier: Programming Language :: Python :: 3
Classifier: Programming Language :: Python :: 3.5
Classifier: Programming Language :: Python :: 3.6
Classifier: Programming Language :: Python :: 3.7
Classifier: Programming Language :: Python :: 3.8
Requires-Python: >=3.5
License-File: LICENSE
License-File: AUTHORS.rst
